mom_scrape/__init__.py
mom_scrape/scrapers.py
mom_scrape-0.0.8.dist-info/licenses/LICENSE
mom_scrape-0.0.8.dist-info/METADATA
mom_scrape-0.0.8.dist-info/WHEEL
mom_scrape-0.0.8.dist-info/top_level.txt
mom_scrape-0.0.8.dist-info/RECORD
