Metadata-Version: 2.4
Name: mom_scrape
Version: 0.0.8
Summary: Script to parse MOM's website for report and stats updates
Author: yxneo
Author-email: yuxuanneo@gmail.com
Classifier: Programming Language :: Python :: 3
Classifier: License :: OSI Approved :: MIT License
Classifier: Operating System :: OS Independent
Requires-Python: >=3.6
License-File: LICENSE
Dynamic: author
Dynamic: author-email
Dynamic: classifier
Dynamic: description
Dynamic: description-content-type
Dynamic: license-file
Dynamic: requires-python
Dynamic: summary
